setup.py
flask_web_args/__init__.py
flask_web_args/validate_wrapper.py
flask_web_args/validator.py
flask_web_args.egg-info/PKG-INFO
flask_web_args.egg-info/SOURCES.txt
flask_web_args.egg-info/dependency_links.txt
flask_web_args.egg-info/not-zip-safe
flask_web_args.egg-info/requires.txt
flask_web_args.egg-info/top_level.txt