Metadata-Version: 1.0
Name: flask-web-args
Version: 0.1.2
Summary: A library to help easily parse/validate web arguments with Flask
Home-page: https://github.com/ftheo/flask-web-args.git
Author: Filippos Theodorakis
Author-email: ftheo3@gmail.com
License: MIT
Keywords: flask arguments args param params web app
Platform: UNKNOWN
